dbgear_editor/__init__.py
dbgear_editor/components/__init__.py
dbgear_editor/components/er_diagram.py
dbgear_editor/components/header.py
dbgear_editor/components/right_sidebar.py
dbgear_editor/components/sidebar.py
dbgear_editor/layout.py
dbgear_editor/main.py
dbgear_editor/project.py
dbgear_editor/routes/__init__.py
dbgear_editor/routes/dashboard.py
dbgear_editor/routes/er_diagram.py
dbgear_editor/routes/procedures.py
dbgear_editor/routes/projects.py
dbgear_editor/routes/tables.py
dbgear_editor/routes/triggers.py
dbgear_editor/routes/views.py
dbgear_editor/settings.py
dbgear_editor/ui/__init__.py
dbgear_editor/ui/common.py
dbgear_editor/ui/procedures.py
dbgear_editor/ui/tables.py
dbgear_editor/ui/triggers.py
dbgear_editor/ui/views.py
dbgear_editor-0.8.2.dist-info/METADATA
dbgear_editor-0.8.2.dist-info/WHEEL
dbgear_editor-0.8.2.dist-info/entry_points.txt
dbgear_editor-0.8.2.dist-info/licenses/LICENSE
dbgear_editor-0.8.2.dist-info/RECORD
