Metadata-Version: 2.4
Name: dbgear-editor
Version: 0.8.2
Summary: FastHTML-based web editor for DBGear schema and data management
License: MIT
License-File: LICENSE
Author: tamuto
Author-email: mutomob@gmail.com
Requires-Python: >=3.12,<4.0
Classifier: License :: OSI Approved :: MIT License
Classifier: Programming Language :: Python :: 3
Classifier: Programming Language :: Python :: 3.12
Classifier: Programming Language :: Python :: 3.13
Classifier: Programming Language :: Python :: 3.14
Requires-Dist: dbgear (>=0.32.1)
Requires-Dist: in4viz (>=0.2.0)
Requires-Dist: monsterui (>=1.0.23,<2.0.0)
Requires-Dist: python-fasthtml (>=0.12.24,<0.13.0)
Requires-Dist: uvicorn (>=0.30.0)
